{
  "schema_version": "V5.2.1-transfermarkt-lineup-value-readiness-r2",
  "generated_at_utc": "2026-07-21T12:14:38+00:00",
  "source": {
    "source_url": "https://pub-e682421888d945d684bcae8890b0ec20.r2.dev/data/player_valuations.csv.gz",
    "compressed_bytes": 5724453,
    "row_count": 507815,
    "columns": [
      "player_id",
      "date",
      "market_value_in_eur",
      "current_club_name",
      "current_club_id",
      "player_club_domestic_competition_id"
    ],
    "player_history_count": 31507
  },
  "season": "2025/26",
  "requested_domains": [
    "ENG_PremierLeague",
    "ESP_LaLiga",
    "GER_Bundesliga",
    "ITA_SerieA",
    "FRA_Ligue1"
  ],
  "passed_domains": [],
  "reports": {
    "ENG_PremierLeague": {
      "competition_id": "ENG_PremierLeague",
      "season": "2025/26",
      "fixture_count": 380,
      "starter_slot_count": 8360,
      "covered_starter_slot_count": 8105,
      "starter_slot_valuation_coverage": 0.9694976076555024,
      "full_home11_valuation_count": 279,
      "full_away11_valuation_count": 278,
      "full_both22_valuation_count": 200,
      "full_both22_valuation_rate": 0.5263157894736842,
      "covered_values_within_180d_rate": 0.7912399753238741,
      "covered_values_within_365d_rate": 0.8207279457125232,
      "valuation_age_days_median": 106,
      "valuation_age_days_p90": 582,
      "unique_missing_player_count": 24,
      "most_frequent_missing_player_ids": [
        {
          "player_id": "515544",
          "missing_fixture_count": 34
        },
        {
          "player_id": "1111589",
          "missing_fixture_count": 30
        },
        {
          "player_id": "432164",
          "missing_fixture_count": 28
        },
        {
          "player_id": "503686",
          "missing_fixture_count": 24
        },
        {
          "player_id": "937941",
          "missing_fixture_count": 21
        },
        {
          "player_id": "314241",
          "missing_fixture_count": 18
        },
        {
          "player_id": "489359",
          "missing_fixture_count": 14
        },
        {
          "player_id": "588989",
          "missing_fixture_count": 14
        },
        {
          "player_id": "1012564",
          "missing_fixture_count": 13
        },
        {
          "player_id": "1056993",
          "missing_fixture_count": 12
        },
        {
          "player_id": "947411",
          "missing_fixture_count": 11
        },
        {
          "player_id": "984096",
          "missing_fixture_count": 6
        },
        {
          "player_id": "282939",
          "missing_fixture_count": 5
        },
        {
          "player_id": "432914",
          "missing_fixture_count": 5
        },
        {
          "player_id": "989112",
          "missing_fixture_count": 4
        },
        {
          "player_id": "605426",
          "missing_fixture_count": 3
        },
        {
          "player_id": "829299",
          "missing_fixture_count": 3
        },
        {
          "player_id": "1064471",
          "missing_fixture_count": 2
        },
        {
          "player_id": "1086258",
          "missing_fixture_count": 2
        },
        {
          "player_id": "998101",
          "missing_fixture_count": 2
        }
      ],
      "status": "PARTIAL",
      "fixture_audit_path": "evidence/transfermarkt_lineup_value_v521/ENG_PremierLeague.jsonl"
    },
    "ESP_LaLiga": {
      "competition_id": "ESP_LaLiga",
      "season": "2025/26",
      "fixture_count": 380,
      "starter_slot_count": 8360,
      "covered_starter_slot_count": 7577,
      "starter_slot_valuation_coverage": 0.9063397129186603,
      "full_home11_valuation_count": 144,
      "full_away11_valuation_count": 140,
      "full_both22_valuation_count": 47,
      "full_both22_valuation_rate": 0.12368421052631579,
      "covered_values_within_180d_rate": 0.5335884914873961,
      "covered_values_within_365d_rate": 0.54045136597598,
      "valuation_age_days_median": 162,
      "valuation_age_days_p90": 705,
      "unique_missing_player_count": 80,
      "most_frequent_missing_player_ids": [
        {
          "player_id": "452483",
          "missing_fixture_count": 33
        },
        {
          "player_id": "603696",
          "missing_fixture_count": 31
        },
        {
          "player_id": "935231",
          "missing_fixture_count": 31
        },
        {
          "player_id": "531404",
          "missing_fixture_count": 30
        },
        {
          "player_id": "593412",
          "missing_fixture_count": 30
        },
        {
          "player_id": "578419",
          "missing_fixture_count": 28
        },
        {
          "player_id": "647435",
          "missing_fixture_count": 28
        },
        {
          "player_id": "705395",
          "missing_fixture_count": 26
        },
        {
          "player_id": "711374",
          "missing_fixture_count": 26
        },
        {
          "player_id": "720518",
          "missing_fixture_count": 25
        },
        {
          "player_id": "626953",
          "missing_fixture_count": 24
        },
        {
          "player_id": "1061122",
          "missing_fixture_count": 21
        },
        {
          "player_id": "1301775",
          "missing_fixture_count": 19
        },
        {
          "player_id": "985383",
          "missing_fixture_count": 19
        },
        {
          "player_id": "929899",
          "missing_fixture_count": 18
        },
        {
          "player_id": "935245",
          "missing_fixture_count": 18
        },
        {
          "player_id": "1063340",
          "missing_fixture_count": 17
        },
        {
          "player_id": "526050",
          "missing_fixture_count": 16
        },
        {
          "player_id": "1124136",
          "missing_fixture_count": 14
        },
        {
          "player_id": "892932",
          "missing_fixture_count": 14
        }
      ],
      "status": "PARTIAL",
      "fixture_audit_path": "evidence/transfermarkt_lineup_value_v521/ESP_LaLiga.jsonl"
    },
    "GER_Bundesliga": {
      "competition_id": "GER_Bundesliga",
      "season": "2025/26",
      "fixture_count": 306,
      "starter_slot_count": 6732,
      "covered_starter_slot_count": 6189,
      "starter_slot_valuation_coverage": 0.9193404634581105,
      "full_home11_valuation_count": 156,
      "full_away11_valuation_count": 151,
      "full_both22_valuation_count": 69,
      "full_both22_valuation_rate": 0.22549019607843138,
      "covered_values_within_180d_rate": 0.7886572952011633,
      "covered_values_within_365d_rate": 0.8233963483599935,
      "valuation_age_days_median": 113,
      "valuation_age_days_p90": 649,
      "unique_missing_player_count": 58,
      "most_frequent_missing_player_ids": [
        {
          "player_id": "667457",
          "missing_fixture_count": 32
        },
        {
          "player_id": "264960",
          "missing_fixture_count": 31
        },
        {
          "player_id": "599733",
          "missing_fixture_count": 30
        },
        {
          "player_id": "470038",
          "missing_fixture_count": 29
        },
        {
          "player_id": "579459",
          "missing_fixture_count": 28
        },
        {
          "player_id": "298603",
          "missing_fixture_count": 27
        },
        {
          "player_id": "957874",
          "missing_fixture_count": 27
        },
        {
          "player_id": "649672",
          "missing_fixture_count": 24
        },
        {
          "player_id": "1035765",
          "missing_fixture_count": 23
        },
        {
          "player_id": "1168219",
          "missing_fixture_count": 20
        },
        {
          "player_id": "605265",
          "missing_fixture_count": 17
        },
        {
          "player_id": "529895",
          "missing_fixture_count": 15
        },
        {
          "player_id": "704155",
          "missing_fixture_count": 15
        },
        {
          "player_id": "377729",
          "missing_fixture_count": 14
        },
        {
          "player_id": "610795",
          "missing_fixture_count": 14
        },
        {
          "player_id": "322517",
          "missing_fixture_count": 13
        },
        {
          "player_id": "897424",
          "missing_fixture_count": 13
        },
        {
          "player_id": "1364454",
          "missing_fixture_count": 12
        },
        {
          "player_id": "333903",
          "missing_fixture_count": 12
        },
        {
          "player_id": "654991",
          "missing_fixture_count": 12
        }
      ],
      "status": "PARTIAL",
      "fixture_audit_path": "evidence/transfermarkt_lineup_value_v521/GER_Bundesliga.jsonl"
    },
    "ITA_SerieA": {
      "competition_id": "ITA_SerieA",
      "season": "2025/26",
      "fixture_count": 379,
      "starter_slot_count": 8338,
      "covered_starter_slot_count": 7839,
      "starter_slot_valuation_coverage": 0.940153514032142,
      "full_home11_valuation_count": 209,
      "full_away11_valuation_count": 207,
      "full_both22_valuation_count": 109,
      "full_both22_valuation_rate": 0.287598944591029,
      "covered_values_within_180d_rate": 0.6365607858145171,
      "covered_values_within_365d_rate": 0.6482969766551856,
      "valuation_age_days_median": 132,
      "valuation_age_days_p90": 702,
      "unique_missing_player_count": 56,
      "most_frequent_missing_player_ids": [
        {
          "player_id": "856530",
          "missing_fixture_count": 34
        },
        {
          "player_id": "867137",
          "missing_fixture_count": 31
        },
        {
          "player_id": "279823",
          "missing_fixture_count": 28
        },
        {
          "player_id": "964580",
          "missing_fixture_count": 28
        },
        {
          "player_id": "728733",
          "missing_fixture_count": 25
        },
        {
          "player_id": "464469",
          "missing_fixture_count": 23
        },
        {
          "player_id": "932187",
          "missing_fixture_count": 22
        },
        {
          "player_id": "1005165",
          "missing_fixture_count": 21
        },
        {
          "player_id": "1159864",
          "missing_fixture_count": 18
        },
        {
          "player_id": "604113",
          "missing_fixture_count": 18
        },
        {
          "player_id": "580451",
          "missing_fixture_count": 17
        },
        {
          "player_id": "1228231",
          "missing_fixture_count": 16
        },
        {
          "player_id": "1077175",
          "missing_fixture_count": 15
        },
        {
          "player_id": "495839",
          "missing_fixture_count": 15
        },
        {
          "player_id": "652054",
          "missing_fixture_count": 14
        },
        {
          "player_id": "459665",
          "missing_fixture_count": 13
        },
        {
          "player_id": "1043646",
          "missing_fixture_count": 12
        },
        {
          "player_id": "827734",
          "missing_fixture_count": 10
        },
        {
          "player_id": "980575",
          "missing_fixture_count": 10
        },
        {
          "player_id": "830365",
          "missing_fixture_count": 9
        }
      ],
      "status": "PARTIAL",
      "fixture_audit_path": "evidence/transfermarkt_lineup_value_v521/ITA_SerieA.jsonl"
    },
    "FRA_Ligue1": {
      "competition_id": "FRA_Ligue1",
      "season": "2025/26",
      "fixture_count": 305,
      "starter_slot_count": 6710,
      "covered_starter_slot_count": 5992,
      "starter_slot_valuation_coverage": 0.8929955290611028,
      "full_home11_valuation_count": 89,
      "full_away11_valuation_count": 104,
      "full_both22_valuation_count": 30,
      "full_both22_valuation_rate": 0.09836065573770492,
      "covered_values_within_180d_rate": 0.5674232309746329,
      "covered_values_within_365d_rate": 0.592456608811749,
      "valuation_age_days_median": 148.0,
      "valuation_age_days_p90": 741,
      "unique_missing_player_count": 78,
      "most_frequent_missing_player_ids": [
        {
          "player_id": "461607",
          "missing_fixture_count": 33
        },
        {
          "player_id": "1088199",
          "missing_fixture_count": 30
        },
        {
          "player_id": "405389",
          "missing_fixture_count": 29
        },
        {
          "player_id": "1113451",
          "missing_fixture_count": 28
        },
        {
          "player_id": "542452",
          "missing_fixture_count": 26
        },
        {
          "player_id": "973949",
          "missing_fixture_count": 26
        },
        {
          "player_id": "851220",
          "missing_fixture_count": 23
        },
        {
          "player_id": "1074628",
          "missing_fixture_count": 22
        },
        {
          "player_id": "1121298",
          "missing_fixture_count": 22
        },
        {
          "player_id": "991054",
          "missing_fixture_count": 22
        },
        {
          "player_id": "1241207",
          "missing_fixture_count": 20
        },
        {
          "player_id": "655217",
          "missing_fixture_count": 20
        },
        {
          "player_id": "691958",
          "missing_fixture_count": 20
        },
        {
          "player_id": "671590",
          "missing_fixture_count": 19
        },
        {
          "player_id": "500053",
          "missing_fixture_count": 17
        },
        {
          "player_id": "796865",
          "missing_fixture_count": 17
        },
        {
          "player_id": "1119456",
          "missing_fixture_count": 16
        },
        {
          "player_id": "1178489",
          "missing_fixture_count": 16
        },
        {
          "player_id": "1182738",
          "missing_fixture_count": 16
        },
        {
          "player_id": "1187942",
          "missing_fixture_count": 15
        }
      ],
      "status": "PARTIAL",
      "fixture_audit_path": "evidence/transfermarkt_lineup_value_v521/FRA_Ligue1.jsonl"
    }
  },
  "failures": {},
  "status": "PARTIAL",
  "formal_weight_change": false,
  "probability_change": false,
  "automatic_promotion": false,
  "pit_policy": "Each starter value is the latest player_valuations record whose date is strictly earlier than the fixture calendar date. Same-day or later valuations are excluded.",
  "lineup_policy": "Uses the already-audited observed Transfermarkt starting-lineup labels for retrospective coverage measurement only. Target-match actual XI is never authorized as a pre-match predictor.",
  "next_step": "If coverage passes, build expected-lineup value features from only earlier observed lineups plus strictly-prior valuations; never use the target match actual XI as prediction input."
}