{
  "schema_version": "V6.6.0-team-configuration-snapshot-r1",
  "observed_at_utc": "2026-07-23T02:48:47+00:00",
  "competition_id": "ITA_SerieA",
  "season": "2026",
  "team_name": "Venezia",
  "provider_ids": {
    "espn_team_id": "17530",
    "espn_league_slug": "ita.1"
  },
  "head_coach": null,
  "players": [
    {
      "player_id": "145138",
      "player_name": "Matteo Grandi",
      "positions": [
        "Goalkeeper",
        "G"
      ],
      "age": 33,
      "shirt_number": "23",
      "squad_status": "Active"
    },
    {
      "player_id": "263816",
      "player_name": "Alessio Pozzi",
      "positions": [
        "Goalkeeper",
        "G"
      ],
      "age": 25,
      "shirt_number": null,
      "squad_status": "Active"
    },
    {
      "player_id": "286390",
      "player_name": "Filippo Neri",
      "positions": [
        "Goalkeeper",
        "G"
      ],
      "age": 23,
      "shirt_number": null,
      "squad_status": "Active"
    },
    {
      "player_id": "289560",
      "player_name": "Filip Stankovic",
      "positions": [
        "Goalkeeper",
        "G"
      ],
      "age": 24,
      "shirt_number": "1",
      "squad_status": "Active"
    },
    {
      "player_id": "181192",
      "player_name": "Ridgeciano Haps",
      "positions": [
        "Defender",
        "D"
      ],
      "age": 33,
      "shirt_number": "5",
      "squad_status": "Active"
    },
    {
      "player_id": "228328",
      "player_name": "Marin Sverko",
      "positions": [
        "Defender",
        "D"
      ],
      "age": 28,
      "shirt_number": "33",
      "squad_status": "Active"
    },
    {
      "player_id": "256763",
      "player_name": "Giorgio Altare",
      "positions": [
        "Defender",
        "D"
      ],
      "age": 27,
      "shirt_number": null,
      "squad_status": "Active"
    },
    {
      "player_id": "275983",
      "player_name": "Thierry Correia",
      "positions": [
        "Defender",
        "D"
      ],
      "age": 27,
      "shirt_number": null,
      "squad_status": "Active"
    },
    {
      "player_id": "278809",
      "player_name": "Michael Venturi",
      "positions": [
        "Defender",
        "D"
      ],
      "age": 27,
      "shirt_number": "16",
      "squad_status": "Active"
    },
    {
      "player_id": "286128",
      "player_name": "Armel Bella-Kotchap",
      "positions": [
        "Defender",
        "D"
      ],
      "age": 24,
      "shirt_number": null,
      "squad_status": "Active"
    },
    {
      "player_id": "291405",
      "player_name": "Bartol Franjic",
      "positions": [
        "Defender",
        "D"
      ],
      "age": 26,
      "shirt_number": null,
      "squad_status": "Active"
    },
    {
      "player_id": "327899",
      "player_name": "Ahmed Sidibé",
      "positions": [
        "Defender",
        "D"
      ],
      "age": 24,
      "shirt_number": "48",
      "squad_status": "Active"
    },
    {
      "player_id": "345152",
      "player_name": "Joel Schingtienne",
      "positions": [
        "Defender",
        "D"
      ],
      "age": 23,
      "shirt_number": "3",
      "squad_status": "Active"
    },
    {
      "player_id": "345713",
      "player_name": "Richie Sagrado",
      "positions": [
        "Defender",
        "D"
      ],
      "age": 22,
      "shirt_number": "20",
      "squad_status": "Active"
    },
    {
      "player_id": "357418",
      "player_name": "Calixte Ligue",
      "positions": [
        "Defender",
        "D"
      ],
      "age": 21,
      "shirt_number": null,
      "squad_status": "Active"
    },
    {
      "player_id": "414161",
      "player_name": "Ale Gomes",
      "positions": [
        "Defender",
        "D"
      ],
      "age": 18,
      "shirt_number": null,
      "squad_status": "Active"
    },
    {
      "player_id": "173282",
      "player_name": "Alfred Duncan",
      "positions": [
        "Midfielder",
        "M"
      ],
      "age": 33,
      "shirt_number": "32",
      "squad_status": "Active"
    },
    {
      "player_id": "221057",
      "player_name": "Toma Basic",
      "positions": [
        "Midfielder",
        "M"
      ],
      "age": 29,
      "shirt_number": null,
      "squad_status": "Active"
    },
    {
      "player_id": "229972",
      "player_name": "Emil Bohinen",
      "positions": [
        "Midfielder",
        "M"
      ],
      "age": 27,
      "shirt_number": "37",
      "squad_status": "Active"
    },
    {
      "player_id": "256106",
      "player_name": "Nunzio Lella",
      "positions": [
        "Midfielder",
        "M"
      ],
      "age": 25,
      "shirt_number": "24",
      "squad_status": "Active"
    },
    {
      "player_id": "263705",
      "player_name": "Gianluca Busio",
      "positions": [
        "Midfielder",
        "M"
      ],
      "age": 24,
      "shirt_number": "6",
      "squad_status": "Active"
    },
    {
      "player_id": "275227",
      "player_name": "Thorir Johann Helgason",
      "positions": [
        "Midfielder",
        "M"
      ],
      "age": 25,
      "shirt_number": null,
      "squad_status": "Active"
    },
    {
      "player_id": "276636",
      "player_name": "Enrique Perez",
      "positions": [
        "Midfielder",
        "M"
      ],
      "age": 29,
      "shirt_number": "71",
      "squad_status": "Active"
    },
    {
      "player_id": "297233",
      "player_name": "Simone Panada",
      "positions": [
        "Midfielder",
        "M"
      ],
      "age": 24,
      "shirt_number": null,
      "squad_status": "Active"
    },
    {
      "player_id": "304279",
      "player_name": "Mattia Compagnon",
      "positions": [
        "Midfielder",
        "M"
      ],
      "age": 24,
      "shirt_number": null,
      "squad_status": "Active"
    },
    {
      "player_id": "307970",
      "player_name": "Bjarki Steinn Bjarkason",
      "positions": [
        "Midfielder",
        "M"
      ],
      "age": 26,
      "shirt_number": "19",
      "squad_status": "Active"
    },
    {
      "player_id": "326032",
      "player_name": "Marko Farji",
      "positions": [
        "Midfielder",
        "M"
      ],
      "age": 22,
      "shirt_number": "11",
      "squad_status": "Active"
    },
    {
      "player_id": "346916",
      "player_name": "Antoine Hainaut",
      "positions": [
        "Midfielder",
        "M"
      ],
      "age": 24,
      "shirt_number": "18",
      "squad_status": "Active"
    },
    {
      "player_id": "361838",
      "player_name": "Lamine Dabo",
      "positions": [
        "Midfielder",
        "M"
      ],
      "age": 22,
      "shirt_number": null,
      "squad_status": "Active"
    },
    {
      "player_id": "366972",
      "player_name": "Matteo Dagasso",
      "positions": [
        "Midfielder",
        "M"
      ],
      "age": 22,
      "shirt_number": "28",
      "squad_status": "Active"
    },
    {
      "player_id": "386951",
      "player_name": "Saad El Haddad",
      "positions": [
        "Midfielder",
        "M"
      ],
      "age": 20,
      "shirt_number": null,
      "squad_status": "Active"
    },
    {
      "player_id": "405754",
      "player_name": "Kornel Lisman",
      "positions": [
        "Midfielder",
        "M"
      ],
      "age": 20,
      "shirt_number": null,
      "squad_status": "Active"
    },
    {
      "player_id": "408725",
      "player_name": "Lorenzo Berardi",
      "positions": [
        "Midfielder",
        "M"
      ],
      "age": 20,
      "shirt_number": null,
      "squad_status": "Active"
    },
    {
      "player_id": "3098213",
      "player_name": "Edoardo Mariani",
      "positions": [
        "Midfielder",
        "M"
      ],
      "age": null,
      "shirt_number": null,
      "squad_status": "Active"
    },
    {
      "player_id": "259357",
      "player_name": "Lion Lauberbach",
      "positions": [
        "Forward",
        "F"
      ],
      "age": 28,
      "shirt_number": "29",
      "squad_status": "Active"
    },
    {
      "player_id": "265926",
      "player_name": "John Yeboah",
      "positions": [
        "Forward",
        "F"
      ],
      "age": 26,
      "shirt_number": "10",
      "squad_status": "Active"
    },
    {
      "player_id": "286317",
      "player_name": "Andrea Adorante",
      "positions": [
        "Forward",
        "F"
      ],
      "age": 26,
      "shirt_number": "9",
      "squad_status": "Active"
    },
    {
      "player_id": "331786",
      "player_name": "Antonio Casas",
      "positions": [
        "Forward",
        "F"
      ],
      "age": 26,
      "shirt_number": "80",
      "squad_status": "Active"
    },
    {
      "player_id": "340139",
      "player_name": "Okoro Obinna",
      "positions": [
        "Forward",
        "F"
      ],
      "age": 21,
      "shirt_number": null,
      "squad_status": "Active"
    },
    {
      "player_id": "342763",
      "player_name": "Albion Rrahmani",
      "positions": [
        "Forward",
        "F"
      ],
      "age": 25,
      "shirt_number": null,
      "squad_status": "Active"
    },
    {
      "player_id": "368005",
      "player_name": "Lorenzo Da Pozzo",
      "positions": [
        "Forward",
        "F"
      ],
      "age": 21,
      "shirt_number": null,
      "squad_status": "Active"
    },
    {
      "player_id": "386952",
      "player_name": "Simone Ascione",
      "positions": [
        "Forward",
        "F"
      ],
      "age": 21,
      "shirt_number": null,
      "squad_status": "Active"
    }
  ],
  "availability": [],
  "transactions": [],
  "sources": [
    {
      "source_name": "ESPN public site API",
      "source_tier": "tier_2",
      "source_url": "https://site.api.espn.com/apis/site/v2/sports/soccer/ita.1/teams/17530/roster",
      "source_observed_at_utc": "2026-07-23T02:48:47+00:00",
      "source_role": "team roster primary machine-readable weekly baseline"
    }
  ],
  "governance": {
    "pit_weekly_snapshot": true,
    "historical_rewrite": false,
    "formal_probability_use": false
  }
}