{
  "schema_version": "V6.6.0-team-configuration-snapshot-r1",
  "observed_at_utc": "2026-07-23T02:48:47+00:00",
  "competition_id": "NOR_Eliteserien",
  "season": "2026",
  "team_name": "Hamarkameratene",
  "provider_ids": {
    "espn_team_id": "21380",
    "espn_league_slug": "nor.1"
  },
  "head_coach": null,
  "players": [
    {
      "player_id": "134074",
      "player_name": "Markus Sandberg",
      "positions": [
        "Goalkeeper",
        "G"
      ],
      "age": 35,
      "shirt_number": "12",
      "squad_status": "Active"
    },
    {
      "player_id": "343349",
      "player_name": "Sander Østraat",
      "positions": [
        "Goalkeeper",
        "G"
      ],
      "age": 21,
      "shirt_number": "13",
      "squad_status": "Active"
    },
    {
      "player_id": "418360",
      "player_name": "Simon Rusen",
      "positions": [
        "Goalkeeper",
        "G"
      ],
      "age": 18,
      "shirt_number": "33",
      "squad_status": "Active"
    },
    {
      "player_id": "223775",
      "player_name": "Luc Mares",
      "positions": [
        "Defender",
        "D"
      ],
      "age": 29,
      "shirt_number": "14",
      "squad_status": "Active"
    },
    {
      "player_id": "285184",
      "player_name": "Fredrik Sjølstad",
      "positions": [
        "Defender",
        "D"
      ],
      "age": 32,
      "shirt_number": "23",
      "squad_status": "Active"
    },
    {
      "player_id": "311151",
      "player_name": "Anton Ekeroth",
      "positions": [
        "Defender",
        "D"
      ],
      "age": 24,
      "shirt_number": "5",
      "squad_status": "Active"
    },
    {
      "player_id": "312901",
      "player_name": "Snorre Nilsen",
      "positions": [
        "Defender",
        "D"
      ],
      "age": 29,
      "shirt_number": "22",
      "squad_status": "Active"
    },
    {
      "player_id": "333786",
      "player_name": "Halvor Opsahl",
      "positions": [
        "Defender",
        "D"
      ],
      "age": 23,
      "shirt_number": "4",
      "squad_status": "Active"
    },
    {
      "player_id": "340144",
      "player_name": "Martin Gjone",
      "positions": [
        "Defender",
        "D"
      ],
      "age": 21,
      "shirt_number": "2",
      "squad_status": "Active"
    },
    {
      "player_id": "346716",
      "player_name": "João Barros",
      "positions": [
        "Defender",
        "D"
      ],
      "age": 25,
      "shirt_number": null,
      "squad_status": "Active"
    },
    {
      "player_id": "389326",
      "player_name": "Ethan Amundsen-Day",
      "positions": [
        "Defender",
        "D"
      ],
      "age": 21,
      "shirt_number": "3",
      "squad_status": "Active"
    },
    {
      "player_id": "397305",
      "player_name": "Ilir Kukleci",
      "positions": [
        "Defender",
        "D"
      ],
      "age": 27,
      "shirt_number": "15",
      "squad_status": "Active"
    },
    {
      "player_id": "399593",
      "player_name": "Ola Nikolai Rye",
      "positions": [
        "Defender",
        "D"
      ],
      "age": 21,
      "shirt_number": "27",
      "squad_status": "Active"
    },
    {
      "player_id": "179771",
      "player_name": "Anders Trondsen",
      "positions": [
        "Midfielder",
        "M"
      ],
      "age": 31,
      "shirt_number": "16",
      "squad_status": "Active"
    },
    {
      "player_id": "252810",
      "player_name": "Vidar Ari Jonsson",
      "positions": [
        "Midfielder",
        "M"
      ],
      "age": 32,
      "shirt_number": "7",
      "squad_status": "Active"
    },
    {
      "player_id": "255624",
      "player_name": "Patrick Metcalfe",
      "positions": [
        "Midfielder",
        "M"
      ],
      "age": 27,
      "shirt_number": "26",
      "squad_status": "Active"
    },
    {
      "player_id": "289428",
      "player_name": "Noah Alexandersson",
      "positions": [
        "Midfielder",
        "M"
      ],
      "age": 24,
      "shirt_number": "21",
      "squad_status": "Active"
    },
    {
      "player_id": "354454",
      "player_name": "Loris Mettler",
      "positions": [
        "Midfielder",
        "M"
      ],
      "age": 27,
      "shirt_number": "10",
      "squad_status": "Active"
    },
    {
      "player_id": "369973",
      "player_name": "Aksel Potur",
      "positions": [
        "Midfielder",
        "M"
      ],
      "age": 24,
      "shirt_number": "17",
      "squad_status": "Active"
    },
    {
      "player_id": "378943",
      "player_name": "Gard Simenstad",
      "positions": [
        "Midfielder",
        "M"
      ],
      "age": 27,
      "shirt_number": "18",
      "squad_status": "Active"
    },
    {
      "player_id": "379949",
      "player_name": "Markus Johnsgård",
      "positions": [
        "Midfielder",
        "M"
      ],
      "age": 27,
      "shirt_number": "8",
      "squad_status": "Active"
    },
    {
      "player_id": "380622",
      "player_name": "William Osnes-Ringen",
      "positions": [
        "Midfielder",
        "M"
      ],
      "age": 19,
      "shirt_number": "6",
      "squad_status": "Active"
    },
    {
      "player_id": "89735",
      "player_name": "Mame Niang",
      "positions": [
        "Forward",
        "F"
      ],
      "age": 20,
      "shirt_number": "29",
      "squad_status": "Active"
    },
    {
      "player_id": "236418",
      "player_name": "Henrik Udahl",
      "positions": [
        "Forward",
        "F"
      ],
      "age": 29,
      "shirt_number": "19",
      "squad_status": "Active"
    },
    {
      "player_id": "333789",
      "player_name": "Jonas Enkerud",
      "positions": [
        "Forward",
        "F"
      ],
      "age": 36,
      "shirt_number": null,
      "squad_status": "Active"
    },
    {
      "player_id": "333793",
      "player_name": "Julian Gonstad",
      "positions": [
        "Forward",
        "F"
      ],
      "age": 20,
      "shirt_number": "20",
      "squad_status": "Active"
    },
    {
      "player_id": "357023",
      "player_name": "Danilo Al-Saed",
      "positions": [
        "Forward",
        "F"
      ],
      "age": 27,
      "shirt_number": null,
      "squad_status": "Active"
    },
    {
      "player_id": "423030",
      "player_name": "David Benjamin",
      "positions": [
        "Forward",
        "F"
      ],
      "age": null,
      "shirt_number": "28",
      "squad_status": "Active"
    }
  ],
  "availability": [],
  "transactions": [],
  "sources": [
    {
      "source_name": "ESPN public site API",
      "source_tier": "tier_2",
      "source_url": "https://site.api.espn.com/apis/site/v2/sports/soccer/nor.1/teams/21380/roster",
      "source_observed_at_utc": "2026-07-23T02:48:47+00:00",
      "source_role": "team roster primary machine-readable weekly baseline"
    }
  ],
  "governance": {
    "pit_weekly_snapshot": true,
    "historical_rewrite": false,
    "formal_probability_use": false
  }
}